{
  "metadata": {
    "organization": "Rolla Lions Club",
    "venue": "Rolla Lions Club Bingo Hall",
    "schedule": "Mondays at 6:45 PM",
    "eventGamesStart": "5:00 PM",
    "closetOpens": "5:45 PM",
    "bingoStarts": "6:45 PM",
    "minimumAge": 16,
    "lastUpdated": "101622",
    "prizePayoutDisclaimer": "We reserve the right to reduce the prize payout consistent with the number of patrons playing each evening"
  },
  "sessionTypes": {
    "5-1": {
      "sessionName": "1st/5th Monday",
      "description": "1st & 5th Monday of Month",
      "totalGames": 17,
      "totalPrizeValue": 2650,
      "games": [
        {
          "gameNumber": 1,
          "category": "Early Bird",
          "color": "N/A",
          "name": "Hard Way Bingo No Free Space",
          "payout": 100,
          "order": 1,
          "timing": "Pre-Regular Session"
        },
        {
          "gameNumber": 2,
          "category": "Early Bird", 
          "color": "N/A",
          "name": "Diagonal & Outside Corners",
          "payout": 100,
          "order": 2,
          "timing": "Pre-Regular Session"
        },
        {
          "gameNumber": 3,
          "category": "Early Bird",
          "color": "N/A", 
          "name": "Small Picture Frame",
          "payout": 100,
          "order": 3,
          "timing": "Pre-Regular Session"
        },
        {
          "gameNumber": 4,
          "category": "Regular",
          "color": "Blue",
          "name": "Regular Bingo or Outside 4 Corners", 
          "payout": 100,
          "order": 4,
          "timing": "Pre-Intermission"
        },
        {
          "gameNumber": 5,
          "category": "Regular",
          "color": "Orange",
          "name": "Number 7",
          "payout": 250,
          "order": 5,
          "timing": "Pre-Intermission"
        },
        {
          "gameNumber": 6,
          "category": "Regular",
          "color": "Green", 
          "name": "Small Diamond",
          "payout": 100,
          "order": 6,
          "timing": "Pre-Intermission"
        },
        {
          "gameNumber": 7,
          "category": "Regular",
          "color": "Yellow",
          "name": "Crazy Picture Frame",
          "payout": 100,
          "order": 7,
          "timing": "Pre-Intermission"
        },
        {
          "gameNumber": 8,
          "category": "Regular",
          "color": "Pink", 
          "name": "Letter X",
          "payout": 250,
          "order": 8,
          "timing": "Pre-Intermission"
        },
        {
          "gameNumber": 9,
          "category": "Pull-Tab",
          "color": "N/A",
          "name": "Event Game",
          "payout": "Varies by Game Selection",
          "order": 9,
          "timing": "Intermission",
          "notes": "Prizes vary based on pull-tab game selection"
        },
        {
          "gameNumber": 10,
          "category": "Regular",
          "color": "Gray",
          "name": "Baseball Diamond",
          "payout": 150,
          "order": 10,
          "timing": "Post-Intermission"
        },
        {
          "gameNumber": 11,
          "category": "Regular", 
          "color": "Olive",
          "name": "6 Pack Anywhere",
          "payout": 150,
          "order": 11,
          "timing": "Post-Intermission"
        },
        {
          "gameNumber": 12,
          "category": "Regular",
          "color": "Brown",
          "name": "Top or Bottom Line",
          "payout": 150,
          "order": 12,
          "timing": "Post-Intermission"
        },
        {
          "gameNumber": 13,
          "category": "Progressive",
          "color": "N/A",
          "name": "Progressive Diamond",
          "payout": "Progressive Prize Varies ($1,000 - $1,199), Consolation $200",
          "order": 13,
          "timing": "Mid-Session",
          "progressiveDetails": {
            "startingJackpot": 1000,
            "maxJackpot": 1199,
            "consolationPrize": 200,
            "increment": "Per week progression",
            "notes": "See sign in hall for current jackpot and winning number"
          }
        },
        {
          "gameNumber": 14,
          "category": "Regular",
          "color": "Red",
          "name": "3 on Top Row & 3 on Bottom Row",
          "payout": 150,
          "order": 14,
          "timing": "Post-Progressive"
        },
        {
          "gameNumber": 15,
          "category": "Regular",
          "color": "Purple", 
          "name": "Double Postage Stamp - Anywhere",
          "payout": 150,
          "order": 15,
          "timing": "Post-Progressive"
        },
        {
          "gameNumber": 16,
          "category": "Regular",
          "color": "Black",
          "name": "Small Kite", 
          "payout": 150,
          "order": 16,
          "timing": "Post-Progressive"
        },
        {
          "gameNumber": 17,
          "category": "Regular",
          "color": "Aqua",
          "name": "Coverall",
          "payout": 500,
          "order": 17,
          "timing": "Final Game"
        }
      ]
    },
    "6-2": {
      "sessionName": "2nd Monday",
      "description": "2nd Monday of Month", 
      "totalGames": 17,
      "totalPrizeValue": 2650,
      "games": [
        {
          "gameNumber": 1,
          "category": "Early Bird",
          "color": "N/A",
          "name": "Hard Way Bingo No Free Space",
          "payout": 100,
          "order": 1,
          "timing": "Pre-Regular Session"
        },
        {
          "gameNumber": 2,
          "category": "Early Bird",
          "color": "N/A", 
          "name": "Diagonal & Outside Corners",
          "payout": 100,
          "order": 2,
          "timing": "Pre-Regular Session"
        },
        {
          "gameNumber": 3,
          "category": "Early Bird",
          "color": "N/A",
          "name": "Small Picture Frame", 
          "payout": 100,
          "order": 3,
          "timing": "Pre-Regular Session"
        },
        {
          "gameNumber": 4,
          "category": "Regular",
          "color": "Blue",
          "name": "Block of 9",
          "payout": 100,
          "order": 4,
          "timing": "Pre-Intermission"
        },
        {
          "gameNumber": 5,
          "category": "Regular",
          "color": "Orange", 
          "name": "Number 7",
          "payout": 250,
          "order": 5,
          "timing": "Pre-Intermission"
        },
        {
          "gameNumber": 6,
          "category": "Regular",
          "color": "Green",
          "name": "Small Diamond",
          "payout": 100,
          "order": 6,
          "timing": "Pre-Intermission"
        },
        {
          "gameNumber": 7,
          "category": "Regular",
          "color": "Yellow",
          "name": "Razor Blade",
          "payout": 100,
          "order": 7,
          "timing": "Pre-Intermission"
        },
        {
          "gameNumber": 8,
          "category": "Regular",
          "color": "Pink",
          "name": "Letter X", 
          "payout": 250,
          "order": 8,
          "timing": "Pre-Intermission"
        },
        {
          "gameNumber": 9,
          "category": "Pull-Tab",
          "color": "N/A",
          "name": "Event Game",
          "payout": "Varies by Game Selection",
          "order": 9,
          "timing": "Intermission",
          "notes": "Prizes vary based on pull-tab game selection"
        },
        {
          "gameNumber": 10,
          "category": "Regular",
          "color": "Gray",
          "name": "5 Around Any Corner",
          "payout": 150,
          "order": 10,
          "timing": "Post-Intermission"
        },
        {
          "gameNumber": 11,
          "category": "Regular",
          "color": "Olive",
          "name": "Double Postage Stamp",
          "payout": 150,
          "order": 11,
          "timing": "Post-Intermission"
        },
        {
          "gameNumber": 12,
          "category": "Regular",
          "color": "Brown",
          "name": "Outside Line", 
          "payout": 150,
          "order": 12,
          "timing": "Post-Intermission"
        },
        {
          "gameNumber": 13,
          "category": "Progressive",
          "color": "N/A",
          "name": "Progressive Diamond",
          "payout": "Progressive Prize Varies ($1,000 - $1,199), Consolation $200",
          "order": 13,
          "timing": "Mid-Session",
          "progressiveDetails": {
            "startingJackpot": 1000,
            "maxJackpot": 1199,
            "consolationPrize": 200,
            "increment": "Per week progression",
            "notes": "See sign in hall for current jackpot and winning number"
          }
        },
        {
          "gameNumber": 14,
          "category": "Regular",
          "color": "Red",
          "name": "Checkmark",
          "payout": 150,
          "order": 14,
          "timing": "Post-Progressive"
        },
        {
          "gameNumber": 15,
          "category": "Regular",
          "color": "Purple",
          "name": "Regular Bingo No Corners - Anywhere",
          "payout": 150,
          "order": 15,
          "timing": "Post-Progressive"
        },
        {
          "gameNumber": 16,
          "category": "Regular",
          "color": "Black", 
          "name": "3 on Top Row & 3 on Bottom Row",
          "payout": 150,
          "order": 16,
          "timing": "Post-Progressive"
        },
        {
          "gameNumber": 17,
          "category": "Regular",
          "color": "Aqua",
          "name": "Coverall",
          "payout": 500,
          "order": 17,
          "timing": "Final Game"
        }
      ]
    },
    "7-3": {
      "sessionName": "3rd Monday",
      "description": "3rd Monday of Month",
      "totalGames": 17,
      "totalPrizeValue": 2650,
      "games": [
        {
          "gameNumber": 1,
          "category": "Early Bird",
          "color": "N/A",
          "name": "Hard Way Bingo No Free Space",
          "payout": 100,
          "order": 1,
          "timing": "Pre-Regular Session"
        },
        {
          "gameNumber": 2,
          "category": "Early Bird",
          "color": "N/A",
          "name": "Diagonal & Outside Corners",
          "payout": 100,
          "order": 2,
          "timing": "Pre-Regular Session"
        },
        {
          "gameNumber": 3,
          "category": "Early Bird",
          "color": "N/A",
          "name": "Small Picture Frame",
          "payout": 100,
          "order": 3,
          "timing": "Pre-Regular Session"
        },
        {
          "gameNumber": 4,
          "category": "Regular",
          "color": "Blue", 
          "name": "6 Pack Anywhere",
          "payout": 100,
          "order": 4,
          "timing": "Pre-Intermission"
        },
        {
          "gameNumber": 5,
          "category": "Regular",
          "color": "Orange",
          "name": "Number 7",
          "payout": 250,
          "order": 5,
          "timing": "Pre-Intermission"
        },
        {
          "gameNumber": 6,
          "category": "Regular",
          "color": "Green",
          "name": "Pyramid",
          "payout": 100,
          "order": 6,
          "timing": "Pre-Intermission"
        },
        {
          "gameNumber": 7,
          "category": "Regular",
          "color": "Yellow",
          "name": "Champagne Glass",
          "payout": 100,
          "order": 7,
          "timing": "Pre-Intermission"
        },
        {
          "gameNumber": 8,
          "category": "Regular",
          "color": "Pink",
          "name": "Letter X",
          "payout": 250,
          "order": 8,
          "timing": "Pre-Intermission"
        },
        {
          "gameNumber": 9,
          "category": "Pull-Tab",
          "color": "N/A",
          "name": "Event Game",
          "payout": "Varies by Game Selection",
          "order": 9,
          "timing": "Intermission",
          "notes": "Pot of Gold, etc. - Prizes vary based on pull-tab game selection"
        },
        {
          "gameNumber": 10,
          "category": "Regular",
          "color": "Gray",
          "name": "Bow Tie",
          "payout": 150,
          "order": 10,
          "timing": "Post-Intermission"
        },
        {
          "gameNumber": 11,
          "category": "Regular",
          "color": "Olive",
          "name": "Outside Line",
          "payout": 150,
          "order": 11,
          "timing": "Post-Intermission"
        },
        {
          "gameNumber": 12,
          "category": "Regular",
          "color": "Brown",
          "name": "L for Lions",
          "payout": 150,
          "order": 12,
          "timing": "Post-Intermission"
        },
        {
          "gameNumber": 13,
          "category": "Progressive",
          "color": "N/A",
          "name": "Progressive Diamond",
          "payout": "Progressive Prize Varies ($1,000 - $1,199), Consolation $200",
          "order": 13,
          "timing": "Mid-Session",
          "progressiveDetails": {
            "startingJackpot": 1000,
            "maxJackpot": 1199,
            "consolationPrize": 200,
            "increment": "Per week progression",
            "notes": "Jackpot starts at $1000 in 17#, then $1050 the second week, $1100 the third week, $1150 the fourth week, then up $10.00 per week to $1190 and then $1.00 per week to maximum of 1199"
          }
        },
        {
          "gameNumber": 14,
          "category": "Regular",
          "color": "Red",
          "name": "Checkmark",
          "payout": 150,
          "order": 14,
          "timing": "Post-Progressive"
        },
        {
          "gameNumber": 15,
          "category": "Regular",
          "color": "Purple",
          "name": "5 Around Any Corner - Anywhere",
          "payout": 150,
          "order": 15,
          "timing": "Post-Progressive"
        },
        {
          "gameNumber": 16,
          "category": "Regular",
          "color": "Black",
          "name": "Small Kite",
          "payout": 150,
          "order": 16,
          "timing": "Post-Progressive"
        },
        {
          "gameNumber": 17,
          "category": "Regular",
          "color": "Aqua",
          "name": "Coverall",
          "payout": 500,
          "order": 17,
          "timing": "Final Game"
        }
      ]
    },
    "8-4": {
      "sessionName": "4th Monday",
      "description": "4th Monday of Month",
      "totalGames": 17,
      "totalPrizeValue": 2650,
      "games": [
        {
          "gameNumber": 1,
          "category": "Early Bird",
          "color": "N/A",
          "name": "Hard Way Bingo No Free Space",
          "payout": 100,
          "order": 1,
          "timing": "Pre-Regular Session"
        },
        {
          "gameNumber": 2,
          "category": "Early Bird",
          "color": "N/A",
          "name": "Diagonal & Outside Corners",
          "payout": 100,
          "order": 2,
          "timing": "Pre-Regular Session"
        },
        {
          "gameNumber": 3,
          "category": "Early Bird",
          "color": "N/A",
          "name": "Small Picture Frame",
          "payout": 100,
          "order": 3,
          "timing": "Pre-Regular Session"
        },
        {
          "gameNumber": 4,
          "category": "Regular",
          "color": "Blue",
          "name": "Block of 9",
          "payout": 100,
          "order": 4,
          "timing": "Pre-Intermission"
        },
        {
          "gameNumber": 5,
          "category": "Regular",
          "color": "Orange",
          "name": "Number 7",
          "payout": 250,
          "order": 5,
          "timing": "Pre-Intermission"
        },
        {
          "gameNumber": 6,
          "category": "Regular",
          "color": "Green",
          "name": "Diamond",
          "payout": 100,
          "order": 6,
          "timing": "Pre-Intermission"
        },
        {
          "gameNumber": 7,
          "category": "Regular",
          "color": "Yellow",
          "name": "Razor Blade",
          "payout": 100,
          "order": 7,
          "timing": "Pre-Intermission"
        },
        {
          "gameNumber": 8,
          "category": "Regular",
          "color": "Pink",
          "name": "Letter X",
          "payout": 250,
          "order": 8,
          "timing": "Pre-Intermission"
        },
        {
          "gameNumber": 9,
          "category": "Pull-Tab",
          "color": "N/A",
          "name": "Event Game",
          "payout": "Varies by Game Selection",
          "order": 9,
          "timing": "Intermission",
          "notes": "Pot of Gold, etc. - Prizes vary based on pull-tab game selection"
        },
        {
          "gameNumber": 10,
          "category": "Regular",
          "color": "Gray",
          "name": "5 Around Any Corner",
          "payout": 150,
          "order": 10,
          "timing": "Post-Intermission"
        },
        {
          "gameNumber": 11,
          "category": "Regular",
          "color": "Olive",
          "name": "Double Postage Stamp",
          "payout": 150,
          "order": 11,
          "timing": "Post-Intermission"
        },
        {
          "gameNumber": 12,
          "category": "Regular",
          "color": "Brown",
          "name": "Outside Line",
          "payout": 150,
          "order": 12,
          "timing": "Post-Intermission"
        },
        {
          "gameNumber": 13,
          "category": "Progressive",
          "color": "N/A",
          "name": "Progressive Diamond",
          "payout": "Progressive Prize Varies ($1,000 - $1,199), Consolation $200",
          "order": 13,
          "timing": "Mid-Session",
          "progressiveDetails": {
            "startingJackpot": 1000,
            "maxJackpot": 1199,
            "consolationPrize": 200,
            "increment": "Per week progression",
            "notes": "Jackpot starts at $1000 in 17#, then progressive weekly increases up to maximum of $1199"
          }
        },
        {
          "gameNumber": 14,
          "category": "Regular",
          "color": "Red",
          "name": "Checkmark",
          "payout": 150,
          "order": 14,
          "timing": "Post-Progressive"
        },
        {
          "gameNumber": 15,
          "category": "Regular",
          "color": "Purple",
          "name": "Regular Bingo - Anywhere",
          "payout": 150,
          "order": 15,
          "timing": "Post-Progressive"
        },
        {
          "gameNumber": 16,
          "category": "Regular",
          "color": "Black",
          "name": "3 on Top Row & 3 on Bottom Row",
          "payout": 150,
          "order": 16,
          "timing": "Post-Progressive"
        },
        {
          "gameNumber": 17,
          "category": "Regular",
          "color": "Aqua",
          "name": "Coverall",
          "payout": 500,
          "order": 17,
          "timing": "Final Game"
        }
      ]
    }
  },
  "gameRules": {
    "general": {
      "minimumAge": 16,
      "ballValidation": "Ball in TV is not good until called",
      "bingoCallProcess": "Do not call Bingo early. Bingo does not have to be on the last number called. It is the player's responsibility to the caller's attention. Yell Bingo loudly and hold your sheet in the air",
      "gameMovement": "We reserve the right to move the Progressive Game elsewhere in the program",
      "ballDropPolicy": "Balls dropped by machine when incorrect Bingo is called are lost even if shown to patrons"
    },
    "progressive": {
      "jackpotProgression": "Jackpot starts at $1000 in 17#, consolation = $200. Then Jackpot = $1050 the second week, $1100 the third week, $1150 the fourth week, then up $10.00 per week to $1190 and then $1.00 per week to a maximum of 1199",
      "winningNumberProgression": "The winning number goes up each week by 1 or 2 until Jackpot is won",
      "referenceNote": "See sign in hall for current details"
    }
  }
}